Metadata-Version: 1.2
Name: flask-ogm
Version: 1.1.0a9
Summary: Add support for the py2neo Object Graph Mapper to your app
Home-page: http://www.flask-ogm.org
Author: Dom Weldon
Author-email: dom.weldon@gmail.com
License: Apache License, Version 2.0
Download-URL: https://github.com/domweldon/flask_ogm/archive/1.1.0.tar.gz
Keywords: graph database py2neo web development neo4j flask
Platform: any
Classifier: Development Status :: 3 - Alpha
Classifier: Environment :: Web Environment
Classifier: Intended Audience :: Developers
Classifier: Operating System :: OS Independent
Classifier: Programming Language :: Python
Classifier: Topic :: Internet :: WWW/HTTP :: Dynamic Content
Classifier: Topic :: Software Development :: Libraries :: Python Modules
Classifier: Programming Language :: Python :: 2.7
Classifier: Programming Language :: Python :: 3.3
Classifier: Programming Language :: Python :: 3.4
Classifier: Programming Language :: Python :: 3.5
Classifier: Programming Language :: Python :: 3.6
Classifier: Topic :: Database
Requires-Python: >=2.7
